django_webhook/__init__.py
django_webhook/admin.py
django_webhook/apps.py
django_webhook/checks.py
django_webhook/forms.py
django_webhook/http.py
django_webhook/migrations/0001_initial.py
django_webhook/migrations/0002_webhookevent.py
django_webhook/migrations/0003_alter_webhook_created_alter_webhook_modified.py
django_webhook/migrations/0004_alter_webhookevent_created_and_more.py
django_webhook/migrations/__init__.py
django_webhook/models.py
django_webhook/settings.py
django_webhook/signals.py
django_webhook/static/webhooks/css/.gitkeep
django_webhook/static/webhooks/images/.gitkeep
django_webhook/static/webhooks/js/.gitkeep
django_webhook/tasks.py
django_webhook/templates/webhooks/.gitkeep
django_webhook/test_factories.py
django_webhook/urls.py
django_webhook/util.py
django_webhook/validators.py
django_webhook-0.0.14.dist-info/LICENSE
django_webhook-0.0.14.dist-info/METADATA
django_webhook-0.0.14.dist-info/WHEEL
django_webhook-0.0.14.dist-info/RECORD
