Metadata-Version: 2.1
Name: django-webhook
Version: 0.0.14
Summary: 
Home-page: https://github.com/danihodovic/django-webhook
License: MIT
Keywords: webhooks,http,microservices
Author: Dani Hodovic
Author-email: you@example.com
Requires-Python: >=3.11,<4.0
Classifier: Framework :: Celery
Classifier: Framework :: Django
Classifier: License :: OSI Approved :: MIT License
Classifier: Programming Language :: Python :: 3
Classifier: Programming Language :: Python :: 3.11
Classifier: Topic :: Internet :: WWW/HTTP
Classifier: Topic :: System :: Distributed Computing
Requires-Dist: celery (==5.*)
Requires-Dist: django (>=4.0,<6.0)
Requires-Dist: django-model-utils (==4.*)
Requires-Dist: requests (==2.*)
Project-URL: Documentation, https://django-webhook.readthedocs.io/en/latest/
Project-URL: Repository, https://github.com/danihodovic/django-webhook
